yandex_gpt_api/__init__.py
yandex_gpt_api/api.py
yandex_gpt_api-0.1.0.dist-info/METADATA
yandex_gpt_api-0.1.0.dist-info/WHEEL
yandex_gpt_api-0.1.0.dist-info/RECORD
