Metadata-Version: 2.4
Name: yandex-gpt-api
Version: 0.1.0
Summary: Библиотека для работы с Yandex GPT API с поддержкой синхронного и асинхронного режимов
Project-URL: Homepage, https://github.com/synergy/yandex-gpt-api
Project-URL: Bug Tracker, https://github.com/synergy/yandex-gpt-api/issues
Author-email: Alexey Savin <avsavin@synergy.ru>
License: MIT
Requires-Python: >=3.7
Requires-Dist: httpx>=0.23.0
Requires-Dist: python-dotenv>=0.19.0
Requires-Dist: requests>=2.25.0
